Metadata-Version: 2.1
Name: sideralib
Version: 3.0.0
Summary: This Python package is for astrology and uses the sidereal system.
Home-page: https://github.com/EH30/sideralib
Author: EH
License: Unlicense
Keywords: Astrology,Sidereal Astrology,Kundli,Sidereal,Tools,Chart,Sidereal Sign,Astrology Chart,Astrology Kundli,Sidereal Library,Ayanamsa,Sidereal Kundli,Sidereal Chart,Sidereal Calculations,Sidereal Number,Sidereal Package,Astro,Astro signs,Astro Number,Sidereal Ayanamsa
Classifier: Programming Language :: Python :: 3.6
Classifier: License :: Freely Distributable
Classifier: Operating System :: OS Independent
Classifier: Development Status :: 5 - Production/Stable
Classifier: Environment :: Other Environment
Classifier: Intended Audience :: Developers
Classifier: Intended Audience :: Science/Research
Classifier: Topic :: Software Development :: Libraries :: Python Modules
License-File: LICENSE
